[{"word": "achievement", "phon": "ə'tʃiːvm(ə)nt", "mean": [{"pos": "n", "trans": "成就；功绩"}]}, {"word": "Quaker", "phon": "'kweikə", "mean": [{"pos": "n", "trans": "教友派信徒；贵格会会员"}]}, {"word": "welfare", "phon": "'welfeə", "mean": [{"pos": "n", "trans": "福利；福利事业"}]}, {"word": "project", "phon": "prəˈdʒekt; ˈprɒdʒekt", "mean": [{"pos": "n", "trans": "项目；工程；规划"}]}, {"word": "institute", "phon": "'ɪnstɪtjuːt", "mean": [{"pos": "n", "trans": "学会；学院；协会"}]}, {"word": "specialist", "phon": "'speʃ(ə)lɪst", "mean": [{"pos": "n", "trans": "专家；专业工作者"}]}, {"word": "specialize", "phon": "'speʃəlaiz", "mean": [{"pos": "v", "trans": "专攻；专门从事；专注于"}]}, {"word": "chimp", "phon": "tʃɪmp", "mean": [{"pos": "n", "trans": "（非洲）黑猩猩"}]}, {"word": "connection", "phon": "kəˈnekʃn", "mean": [{"pos": "n", "trans": "关系；连接"}]}, {"word": "campaign", "phon": "kæm'peɪn", "mean": [{"pos": "n", "trans": "运动；战役"}, {"pos": "v", "trans": "作战；参加运动"}]}, {"word": "organization", "phon": "ˌɔːɡənaɪ'zeɪʃn", "mean": [{"pos": "n", "trans": "组织；机构；团体"}]}, {"word": "behave", "phon": "bɪ'heɪv", "mean": [{"pos": "v", "trans": "（举止或行为）表现"}]}, {"word": "behaviour", "phon": "bɪ'heɪvjə", "mean": [{"pos": "v", "trans": "(等于behaior)行为；举止；习性"}]}, {"word": "shade", "phon": "ʃeɪd", "mean": [{"pos": "n", "trans": "荫；阴凉处"}, {"pos": "v", "trans": "遮住光线"}]}, {"word": "worthwhile", "phon": "wɜːθ'waɪl", "mean": [{"pos": "adj", "trans": "值得的；值得做的"}]}, {"word": "nest", "phon": "nest", "mean": [{"pos": "n", "trans": "巢；窝"}]}, {"word": "bond", "phon": "bɒnd", "mean": [{"pos": "n", "trans": "联系；关系；结合；纽带"}]}, {"word": "observe", "phon": "əb'zɜːv", "mean": [{"pos": "v", "trans": "观察；观测；遵守"}]}, {"word": "observation", "phon": "ɒbzə'veɪʃ(ə)n", "mean": [{"pos": "n", "trans": "观察；观测"}]}, {"word": "childhood", "phon": "'tʃaɪldhʊd", "mean": [{"pos": "n", "trans": "童年；幼年时代"}]}, {"word": "outspoken", "phon": "aʊt'spəʊk(ə)n", "mean": [{"pos": "adj", "trans": "直言的；坦诚"}]}, {"word": "respect", "phon": "rɪ'spekt", "mean": [{"pos": "n", "trans": "尊敬；尊重；敬意"}, {"pos": "v", "trans": "尊敬；尊重"}]}, {"word": "argue", "phon": "'ɑːgjuː", "mean": [{"pos": "v", "trans": "争论；讨论；辩论"}]}, {"word": "argument", "phon": "'ɑːgjʊm(ə)nt", "mean": [{"pos": "n", "trans": "争论；争辩；争吵"}]}, {"word": "entertainment", "phon": "ˌentə'teɪnmənt", "mean": [{"pos": "n", "trans": "娱乐；娱乐表演；款待"}]}, {"word": "crowd", "phon": "kraʊd", "mean": [{"pos": "n", "trans": "人群；观众"}, {"pos": "v", "trans": "挤满；使拥挤"}]}, {"word": "inspire", "phon": "ɪn'spaɪə", "mean": [{"pos": "v", "trans": "鼓舞；激发；启示"}]}, {"word": "inspiration", "phon": "ˌɪnspəˈreɪʃn", "mean": [{"pos": "n", "trans": "灵感；鼓舞"}]}, {"word": "support", "phon": "sə'pɔːt", "mean": [{"pos": "v", "trans": "支持；拥护"}, {"pos": "n", "trans": "支持；拥护"}]}, {"word": "refer", "phon": "rɪ'fɜː", "mean": [{"pos": "v", "trans": "谈到；查阅；参考"}]}, {"word": "audience", "phon": "'ɔːdɪəns", "mean": [{"pos": "n", "trans": "观众；听众；读者"}]}, {"word": "career", "phon": "kə'rɪə", "mean": [{"pos": "n", "trans": "事业；生涯"}]}, {"word": "rate", "phon": "reɪt", "mean": [{"pos": "n", "trans": "比率；速度"}]}, {"word": "sickness", "phon": "'sɪknɪs", "mean": [{"pos": "n", "trans": "疾病；恶心"}]}, {"word": "intend", "phon": "ɪn'tend", "mean": [{"pos": "v", "trans": "计划；打算"}]}, {"word": "emergency", "phon": "ɪ'mɜːdʒ(ə)nsɪ", "mean": [{"pos": "n", "trans": "突发事件；紧急情况"}]}, {"word": "generation", "phon": "dʒenə'reɪʃ(ə)n", "mean": [{"pos": "n", "trans": "一代；一辈"}]}, {"word": "determination", "phon": "dɪ,tɜːmɪ'neɪʃ(ə)n", "mean": [{"pos": "n", "trans": "决心"}]}, {"word": "kindness", "phon": "'kaɪn(d)nɪs", "mean": [{"pos": "n", "trans": "仁慈；好意"}]}, {"word": "considerate", "phon": "kən'sɪd(ə)rət", "mean": [{"pos": "adj", "trans": "考虑周到的"}]}, {"word": "consideration", "phon": "kənsɪdə'reɪʃ(ə)n", "mean": [{"pos": "n", "trans": "考虑"}]}, {"word": "deliver", "phon": "dɪ'lɪvə", "mean": [{"pos": "v", "trans": "递送；生（小孩儿）；接生；发表（演说等）"}]}, {"word": "modest", "phon": "'mɒdɪst", "mean": [{"pos": "adj", "trans": "谦虚的；谦让的；适度的"}]}, {"word": "statistic", "phon": "stə'tɪstɪk", "mean": [{"pos": "n", "trans": "[pl]统计数字；统计资料；[sg]数据；统计；"}]}, {"word": "sunburnt", "phon": "'sʌnbɜːnt", "mean": [{"pos": "adj", "trans": "晒黑的(等于sunburned)"}]}, {"word": "struggle", "phon": "'strʌg(ə)l", "mean": [{"pos": "v", "trans": "拼搏；努力；斗争"}]}, {"word": "decade", "phon": "'dekeɪd; dɪ'keɪd", "mean": [{"pos": "n", "trans": "十年；十年期"}]}, {"word": "super", "phon": "'suːpə; 'sjuː-", "mean": [{"pos": "adj", "trans": "特级的；超级的"}]}, {"word": "hybrid", "phon": "'haɪbrɪd", "mean": [{"pos": "adj", "trans": "混合的；杂种的"}, {"pos": "n", "trans": "杂交种；混血儿"}]}, {"word": "output", "phon": "'aʊtpʊt", "mean": [{"pos": "n", "trans": "产量；输出量"}]}, {"word": "strain", "phon": "streɪn", "mean": [{"pos": "n", "trans": "品种；种类"}]}, {"word": "crop", "phon": "krɒp", "mean": [{"pos": "n", "trans": "庄稼；农作物"}]}, {"word": "hunger", "phon": "'hʌŋgə", "mean": [{"pos": "n", "trans": "饥饿；欲望"}, {"pos": "v", "trans": "（使）饥饿"}]}, {"word": "disturbing", "phon": "dɪ'stɜːbɪŋ", "mean": [{"pos": "adj", "trans": "引起烦恼的；令人不安的"}]}, {"word": "expand", "phon": "ɪk'spænd; ek-", "mean": [{"pos": "v", "trans": "使变大；扩展"}]}, {"word": "circulate", "phon": "'sɜːkjʊleɪt", "mean": [{"pos": "v", "trans": "循环；流传"}]}, {"word": "Vietnam", "phon": "ˌvjet'næm", "mean": [{"pos": "n", "trans": "越南（东南亚国家）"}]}, {"word": "battle", "phon": "'bæt(ə)l", "mean": [{"pos": "n", "trans": "战役；战斗；较量；斗争"}, {"pos": "v", "trans": "搏斗；奋斗"}]}, {"word": "rid", "phon": "rɪd", "mean": [{"pos": "v", "trans": "摆脱；除去"}]}, {"word": "freedom", "phon": "'friːdəm", "mean": [{"pos": "n", "trans": "自由；自主"}]}, {"word": "therefore", "phon": "'ðeəfɔː", "mean": [{"pos": "adv", "trans": "因为；所以；因而"}]}, {"word": "equip", "phon": "ɪ'kwɪp", "mean": [{"pos": "v", "trans": "配备；装备"}]}, {"word": "sorghum", "phon": "'sɔːgəm", "mean": [{"pos": "n", "trans": "高粱"}]}, {"word": "grain", "phon": "greɪn", "mean": [{"pos": "n", "trans": "谷物；粮食；颗粒"}]}, {"word": "peanut", "phon": "'piːnʌt", "mean": [{"pos": "n", "trans": "花生"}]}, {"word": "export", "phon": "ˈekspɔːt；ɪkˈ-", "mean": [{"pos": "v", "trans": "出口；输出"}]}, {"word": "nationality", "phon": "ˌnæʃəˈnælətɪ", "mean": [{"pos": "n", "trans": "国籍"}]}, {"word": "occupation", "phon": "ɒkjʊ'peɪʃ(ə)n", "mean": [{"pos": "n", "trans": "工作；职业；占领"}]}, {"word": "personality", "phon": "pɜːsə'nælɪtɪ", "mean": [{"pos": "n", "trans": "性格；个性；人格"}]}, {"word": "confuse", "phon": "kən'fjuːz", "mean": [{"pos": "v", "trans": "使迷惑"}]}, {"word": "regret", "phon": "rɪ'gret", "mean": [{"pos": "v", "trans": "遗憾；惋惜"}, {"pos": "n", "trans": "遗憾；懊悔"}]}, {"word": "chemical", "phon": "'kemɪk(ə)l", "mean": [{"pos": "adj", "trans": "化学的；关于化学的"}]}, {"word": "organic", "phon": "ɔː'gænɪk", "mean": [{"pos": "adj", "trans": "有机的；器官的"}]}, {"word": "fertile", "phon": "'fɜːtaɪl", "mean": [{"pos": "adj", "trans": "肥沃的；富饶的"}]}, {"word": "fertilizer", "phon": "'fɜːtɪlaɪzə", "mean": [{"pos": "n", "trans": "肥料；化肥"}]}, {"word": "production", "phon": "prə'dʌkʃ(ə)n", "mean": [{"pos": "n", "trans": "生产；制造"}]}, {"word": "bacteria", "phon": "bæk'tɪərɪə", "mean": [{"pos": "n", "trans": "（bacterium的复数形式）细菌"}]}, {"word": "pest", "phon": "pest", "mean": [{"pos": "n", "trans": "害虫；害兽；害鸟"}]}, {"word": "nutrition", "phon": "njʊ'trɪʃ(ə)n", "mean": [{"pos": "n", "trans": "营养;滋养"}]}, {"word": "mineral", "phon": "'mɪn(ə)r(ə)l", "mean": [{"pos": "n", "trans": "矿物；矿石"}]}, {"word": "discovery", "phon": "dɪ'skʌv(ə)rɪ", "mean": [{"pos": "n", "trans": "发现；发觉"}]}, {"word": "focus", "phon": "'fəʊkəs", "mean": [{"pos": "n", "trans": "焦点；中心点"}, {"pos": "v", "trans": "集中"}]}, {"word": "soil", "phon": "sɔɪl", "mean": [{"pos": "n", "trans": "土壤"}]}, {"word": "reduce", "phon": "rɪ'djuːs", "mean": [{"pos": "v", "trans": "减少；减缩"}]}, {"word": "soybean", "phon": "'sɒɪbiːn", "mean": [{"pos": "n", "trans": "(等于soyabean) 大豆"}]}, {"word": "root", "phon": "ruːt", "mean": [{"pos": "n", "trans": "根；根源"}]}, {"word": "skim", "phon": "skɪm", "mean": [{"pos": "v", "trans": "浏览；略读"}]}, {"word": "underline", "phon": "ʌndə'laɪn", "mean": [{"pos": "v", "trans": "画底线标出；强调"}]}, {"word": "summary", "phon": "'sʌm(ə)rɪ", "mean": [{"pos": "n", "trans": "总结；摘要；概要"}]}, {"word": "comment", "phon": "'kɒment", "mean": [{"pos": "n", "trans": "评论；议论"}, {"pos": "v", "trans": "表达意见；作出评论"}]}, {"word": "producer", "phon": "prə'djuːsə", "mean": [{"pos": "n", "trans": "制片人；生产者"}]}, {"word": "industrial", "phon": "ɪn'dʌstrɪəl", "mean": [{"pos": "adj", "trans": "工业的；产业的"}]}, {"word": "humour", "phon": "'hjuːmə", "mean": [{"pos": "n", "trans": "幽默；滑稽"}]}, {"word": "punchline", "phon": "'pʌn(t)ʃlaɪn", "mean": [{"pos": "n", "trans": "故事、笑话等中的妙语；关键语"}]}, {"word": "verbal", "phon": "'vɜːb(ə)l", "mean": [{"pos": "adj", "trans": "口头的"}]}, {"word": "nonverbal", "phon": "nɒn'vɜːbəl", "mean": [{"pos": "adj", "trans": "不用语言的"}]}, {"word": "mime", "phon": "maɪm", "mean": [{"pos": "n", "trans": "哑剧"}]}, {"word": "comedy", "phon": "'kɒmɪdɪ", "mean": [{"pos": "n", "trans": "喜剧"}]}, {"word": "brighten", "phon": "'braɪt(ə)n", "mean": [{"pos": "v", "trans": "使更明亮"}]}, {"word": "depressed", "phon": "dɪ'prest", "mean": [{"pos": "adj", "trans": "忧愁的；沮丧的"}]}, {"word": "content", "phon": "kən'tent", "mean": [{"pos": "adj", "trans": "满足的；满意的"}, {"pos": "n", "trans": "满足"}, {"pos": "v", "trans": "使满足"}]}, {"word": "performer", "phon": "pə'fɔːmə(r)", "mean": [{"pos": "n", "trans": "表演者；演出者"}]}, {"word": "astonish", "phon": "ə'stɒnɪʃ", "mean": [{"pos": "v", "trans": "使惊诧"}]}, {"word": "astonishing", "phon": "ə'stɒnɪʃɪŋ", "mean": [{"pos": "adj", "trans": "令人感到惊讶的"}]}, {"word": "fortunate", "phon": "'fɔːtʃ(ə)nət", "mean": [{"pos": "adj", "trans": "幸运的；吉利的"}]}, {"word": "unfortunately", "phon": "ʌnˈfɔːtʃənətli", "mean": [{"pos": "adv", "trans": "不幸地"}]}, {"word": "teens", "phon": "tiːnz", "mean": [{"pos": "n", "trans": "十几岁（13至19岁的年龄）"}]}, {"word": "ordinary", "phon": "'ɔːdɪn(ə)rɪ; -d(ə)n-", "mean": [{"pos": "adj", "trans": "平常的；普通的"}]}, {"word": "bored", "phon": "bɔːd", "mean": [{"pos": "adj", "trans": "厌烦的"}]}, {"word": "subtle", "phon": "'sʌt(ə)l", "mean": [{"pos": "adj", "trans": "微妙的，细微的"}]}, {"word": "entertain", "phon": "entə'teɪn", "mean": [{"pos": "v", "trans": "款待；使欢乐"}]}, {"word": "entertaining", "phon": "entə'teɪnɪŋ", "mean": [{"pos": "adj", "trans": "愉快的；有趣的"}]}, {"word": "charming", "phon": "'tʃɑːmɪŋ", "mean": [{"pos": "adj", "trans": "迷人的；有魅力的"}]}, {"word": "tramp", "phon": "træmp", "mean": [{"pos": "n", "trans": "流浪汉；行乞者"}]}, {"word": "throughout", "phon": "θruː'aʊt", "mean": [{"pos": "prep&adv", "trans": "遍及；在…各处；在整个期间，自始至终"}]}, {"word": "homeless", "phon": "'həʊmlɪs", "mean": [{"pos": "adj", "trans": "无家的；无家可归的"}]}, {"word": "moustache", "phon": "mə'stɑːʃ", "mean": [{"pos": "n", "trans": "小胡子"}]}, {"word": "worn", "phon": "wɔːn", "mean": [{"pos": "adj", "trans": "用旧的；用坏的；破烂的"}]}, {"word": "worn-out", "phon": "'wɔːn'aʊt", "mean": [{"pos": "adj", "trans": "磨破的；穿旧的"}]}, {"word": "failure", "phon": "'feɪljə", "mean": [{"pos": "n", "trans": "失败"}]}, {"word": "optimism", "phon": "'ɒptɪmɪz(ə)m", "mean": [{"pos": "n", "trans": "乐观；乐观主义"}]}, {"word": "overcome", "phon": "əʊvə'kʌm", "mean": [{"pos": "v", "trans": "战胜；克服"}]}, {"word": "underdog", "phon": "'ʌndədɒg", "mean": [{"pos": "n", "trans": "失败者；处于劣势的一方"}]}, {"word": "snowstorm", "phon": "'snəʊstɔːm", "mean": [{"pos": "n", "trans": "暴风雪"}]}, {"word": "leather", "phon": "'leðə", "mean": [{"pos": "n", "trans": "皮革"}]}, {"word": "lace", "phon": "leɪs", "mean": [{"pos": "n", "trans": "花边；鞋带"}]}, {"word": "chew", "phon": "tʃuː", "mean": [{"pos": "v", "trans": "嚼碎；咀嚼（食物）"}]}, {"word": "mouthful", "phon": "'maʊθfʊl; -f(ə)l", "mean": [{"pos": "n", "trans": "一口；满口"}]}, {"word": "enjoyment", "phon": "ɪn'dʒɒɪmənt", "mean": [{"pos": "n", "trans": "享受；欢乐；乐趣"}]}, {"word": "convince", "phon": "kən'vɪns", "mean": [{"pos": "v", "trans": "使信服"}]}, {"word": "convincing", "phon": "kən'vɪnsɪŋ", "mean": [{"pos": "adj", "trans": "令人信服的"}]}, {"word": "direct", "phon": "dəˈrekt; daɪˈrekt", "mean": [{"pos": "v", "trans": "导演；指示；指挥"}, {"pos": "adj", "trans": "直接的；笔直的；率直的，坦率的"}]}, {"word": "Oscar", "phon": "'ɒskə", "mean": [{"pos": "n", "trans": "奥斯卡"}]}, {"word": "outstanding", "phon": "aʊt'stændɪŋ", "mean": [{"pos": "adj", "trans": "杰出的；显著的；突出的"}]}, {"word": "Switzerland", "phon": "ˈswɪtsələnd", "mean": [{"pos": "n", "trans": "瑞士（欧洲中部国家）"}]}, {"word": "confidence", "phon": "'kɒnfɪd(ə)ns", "mean": [{"pos": "n", "trans": "信心；信念"}]}, {"word": "costume", "phon": "kɒstjuːm", "mean": [{"pos": "n", "trans": "戏装；服装"}]}, {"word": "gesture", "phon": "'dʒestʃə", "mean": [{"pos": "n", "trans": "手势；姿态"}, {"pos": "v", "trans": "做手势"}]}, {"word": "particular", "phon": "pəˈtɪkjʊlə(r)", "mean": [{"pos": "adj", "trans": "特殊的；特别的"}, {"pos": "n", "trans": "细节"}]}, {"word": "particularly", "phon": "pə'tɪkjʊləlɪ", "mean": [{"pos": "adv", "trans": "特别，尤其"}]}, {"word": "occasion", "phon": "ə'keɪʒ(ə)n", "mean": [{"pos": "n", "trans": "时刻"}]}, {"word": "budget", "phon": "'bʌdʒɪt", "mean": [{"pos": "n", "trans": "预算；开支"}]}, {"word": "actress", "phon": "'æktrɪs", "mean": [{"pos": "n", "trans": "女演员"}]}, {"word": "slide", "phon": "slaɪd", "mean": [{"pos": "v", "trans": "（使）滑动；（使）滑行"}, {"pos": "n", "trans": "滑梯；下降，跌落；幻灯片"}]}, {"word": "amuse", "phon": "ə'mjuːz", "mean": [{"pos": "v", "trans": "使发笑；使愉快"}]}, {"word": "amusing", "phon": "ə'mjuːzɪŋ", "mean": [{"pos": "adj", "trans": "好笑的；有趣的"}]}, {"word": "pancake", "phon": "'pænkeɪk", "mean": [{"pos": "n", "trans": "烙饼；薄饼"}]}, {"word": "explanation", "phon": "eksplə'neɪʃ(ə)n", "mean": [{"pos": "n", "trans": "解释"}]}, {"word": "detective", "phon": "dɪ'tektɪv", "mean": [{"pos": "n", "trans": "侦探"}]}, {"word": "mountainous", "phon": "'maʊntɪnəs", "mean": [{"pos": "adj", "trans": "多山的；山一般的"}]}, {"word": "whisper", "phon": "'wɪspə", "mean": [{"pos": "n", "trans": "耳语；低语"}, {"pos": "v", "trans": "低语；小声说"}]}, {"word": "vast", "phon": "vɑːst", "mean": [{"pos": "adj", "trans": "巨大的；辽阔的"}]}, {"word": "rhythm", "phon": "'rɪð(ə)m", "mean": [{"pos": "n", "trans": "节奏"}]}, {"word": "mess", "phon": "mes", "mean": [{"pos": "n", "trans": "脏或乱的状态"}]}, {"word": "react", "phon": "rɪ'ækt", "mean": [{"pos": "v", "trans": "作出反应；回应"}]}, {"word": "porridge", "phon": "'pɒrɪdʒ", "mean": [{"pos": "n", "trans": "粥；麦片粥"}]}, {"word": "drunk", "phon": "drʌŋk", "mean": [{"pos": "adj", "trans": "醉的"}]}, {"word": "statement", "phon": "'steɪtm(ə)nt", "mean": [{"pos": "n", "trans": "陈述；说明"}]}, {"word": "greet", "phon": "griːt", "mean": [{"pos": "v", "trans": "迎接；问候"}]}, {"word": "represent", "phon": "reprɪ'zent", "mean": [{"pos": "v", "trans": "代表；象征"}]}, {"word": "association", "phon": "əˌsəʊsɪˈeɪʃn", "mean": [{"pos": "n", "trans": "社团；联系；联想"}]}, {"word": "dormitory", "phon": "ˈdɔ:mɪtrɪ", "mean": [{"pos": "n", "trans": "宿舍"}]}, {"word": "canteen", "phon": "kæn'tiːn", "mean": [{"pos": "n", "trans": "食堂"}]}, {"word": "flight", "phon": "flaɪt", "mean": [{"pos": "n", "trans": "航班；飞行"}]}, {"word": "curious", "phon": "'kjʊərɪəs", "mean": [{"pos": "adj", "trans": "好奇的"}]}, {"word": "curiously", "phon": "'kjʊərɪəslɪ", "mean": [{"pos": "adv", "trans": "好奇地"}]}, {"word": "Colombia", "phon": "kə'lʌmbiə", "mean": [{"pos": "n", "trans": "哥伦比亚（南美洲国家）"}]}, {"word": "approach", "phon": "ə'prəʊtʃ", "mean": [{"pos": "v", "trans": "接近；靠近；走近"}, {"pos": "n", "trans": "接近；方法"}]}, {"word": "cheek", "phon": "tʃiːk", "mean": [{"pos": "n", "trans": "面颊"}]}, {"word": "defend", "phon": "dɪ'fend", "mean": [{"pos": "v", "trans": "保护；保卫"}]}, {"word": "defence", "phon": "dɪ'fens", "mean": [{"pos": "n", "trans": "防御；保卫"}]}, {"word": "major", "phon": "'meɪdʒə", "mean": [{"pos": "adj", "trans": "主要的"}]}, {"word": "misunderstand", "phon": ",mɪsʌndə'stænd", "mean": [{"pos": "v", "trans": "误解，误会"}]}, {"word": "misunderstanding", "phon": ",mɪsʌndə'stændɪŋ", "mean": [{"pos": "n", "trans": "误解；误会"}]}, {"word": "Jordan", "phon": "'dʒɔ:dən", "mean": [{"pos": "n", "trans": "约旦（西亚国家）"}]}, {"word": "dash", "phon": "dæʃ", "mean": [{"pos": "v", "trans": "猛冲；突进"}]}, {"word": "adult", "phon": "'ædʌlt; ə'dʌlt", "mean": [{"pos": "n", "trans": "成人；成年人"}, {"pos": "adj", "trans": "成人的；成熟的"}]}, {"word": "simply", "phon": "'sɪmplɪ", "mean": [{"pos": "adv", "trans": "简单地；只"}]}, {"word": "Muslim", "phon": "ˈmʊzlɪm;ˈmʌzlɪm;ˈmʊzləm;ˈmʌzləm", "mean": [{"pos": "n & adj", "trans": "穆斯林（的）；伊斯兰教信徒（的）"}]}, {"word": "spoken", "phon": "'spəʊk(ə)n", "mean": [{"pos": "adj", "trans": "口语的"}]}, {"word": "posture", "phon": "'pɒstʃə", "mean": [{"pos": "n", "trans": "姿态；体态"}]}, {"word": "Spain", "phon": "spein", "mean": [{"pos": "n", "trans": "西班牙（欧洲国家）"}]}, {"word": "Italy", "phon": "'ɪtəlɪ", "mean": [{"pos": "n", "trans": "意大利（欧洲国家）"}]}, {"word": "likely", "phon": "'laɪklɪ", "mean": [{"pos": "adj", "trans": "可能的"}]}, {"word": "crossroads", "phon": "'krɒsrəʊdz", "mean": [{"pos": "n", "trans": "十字路口"}]}, {"word": "employee", "phon": "ɪmˈplɔɪi;ˌemplɔɪˈi:", "mean": [{"pos": "n", "trans": "雇员"}]}, {"word": "frown", "phon": "fraʊn", "mean": [{"pos": "v", "trans": "皱眉；蹙额"}]}, {"word": "misread", "phon": "mɪs'riːd", "mean": [{"pos": "v", "trans": "误解；读错"}]}, {"word": "facial", "phon": "'feɪʃ(ə)l", "mean": [{"pos": "adj", "trans": "面部的"}]}, {"word": "function", "phon": "'fʌŋ(k)ʃ(ə)n", "mean": [{"pos": "n", "trans": "作用；功能；职能"}, {"pos": "v", "trans": "起作用；运转"}]}, {"word": "ease", "phon": "iːz", "mean": [{"pos": "n", "trans": "安逸；舒适"}, {"pos": "v", "trans": "减轻（痛苦；忧虑）"}]}, {"word": "truly", "phon": "'truːlɪ", "mean": [{"pos": "adv", "trans": "真实地；真诚地"}]}, {"word": "false", "phon": "fɔːls; fɒls", "mean": [{"pos": "adj", "trans": "假的；错误的"}]}, {"word": "anger", "phon": "'æŋgə", "mean": [{"pos": "n", "trans": "怒气；怒火"}]}, {"word": "fist", "phon": "fɪst", "mean": [{"pos": "n", "trans": "拳头"}]}, {"word": "yawn", "phon": "jɔːn", "mean": [{"pos": "v", "trans": "打呵欠"}]}, {"word": "respectful", "phon": "rɪ'spek(t)fʊl; -f(ə)l", "mean": [{"pos": "adj", "trans": "恭敬的"}]}, {"word": "subjective", "phon": "səb'dʒektɪv", "mean": [{"pos": "adj", "trans": "主观的"}]}, {"word": "hug", "phon": "hʌg", "mean": [{"pos": "v", "trans": "拥抱"}]}, {"word": "rank", "phon": "ræŋk", "mean": [{"pos": "n", "trans": "等级；军衔"}]}, {"word": "cassette", "phon": "kə'set", "mean": [{"pos": "n", "trans": "磁带"}]}, {"word": "theme", "phon": "θiːm", "mean": [{"pos": "n", "trans": "题目；主题（曲）"}]}, {"word": "central", "phon": "'sentr(ə)l", "mean": [{"pos": "adj", "trans": "中心的；中央的"}]}, {"word": "various", "phon": "'veərɪəs", "mean": [{"pos": "adj", "trans": "不同的；各种各样的"}]}, {"word": "cartoon", "phon": "kɑː'tuːn", "mean": [{"pos": "n", "trans": "动画片；漫画"}]}, {"word": "whichever", "phon": "wɪtʃ'evə", "mean": [{"pos": "pron", "trans": "无论哪一个；任何一个"}]}, {"word": "pirate", "phon": "ˈpaɪərət", "mean": [{"pos": "n", "trans": "海盗；盗版者"}]}, {"word": "fantasy", "phon": "'fæntəsɪ; -zɪ", "mean": [{"pos": "n", "trans": "幻想"}]}, {"word": "amusement", "phon": "ə'mjuːzm(ə)nt", "mean": [{"pos": "n", "trans": "消遣；娱乐（活动）"}]}, {"word": "swing", "phon": "swɪŋ", "mean": [{"pos": "n", "trans": "秋千；摇摆"}, {"pos": "v", "trans": "摇摆；摆动"}]}, {"word": "attraction", "phon": "ə'trækʃ(ə)n", "mean": [{"pos": "n", "trans": "有吸引力的事物"}]}, {"word": "tourism", "phon": "'tʊərɪz(ə)m", "mean": [{"pos": "n", "trans": "旅游业"}]}, {"word": "wherever", "phon": "weər'evə", "mean": [{"pos": "pron", "trans": "无论在什么地方；各处"}]}, {"word": "unique", "phon": "juː'niːk", "mean": [{"pos": "adj", "trans": "独一无二的；仅有的"}]}, {"word": "carpenter", "phon": "ˈkɑːpəntə(r)", "mean": [{"pos": "n", "trans": "木匠"}]}, {"word": "craftsman", "phon": "'krɑːf(t)smən", "mean": [{"pos": "n", "trans": "匠人；能工巧匠"}]}, {"word": "engine", "phon": "'endʒɪn", "mean": [{"pos": "n", "trans": "引擎；发动机"}]}, {"word": "bald", "phon": "bɔːld", "mean": [{"pos": "adj", "trans": "秃头的"}]}, {"word": "preserve", "phon": "prɪ'zɜːv", "mean": [{"pos": "v", "trans": "保存；保留"}, {"pos": "n", "trans": "保护区"}]}, {"word": "length", "phon": "leŋθ", "mean": [{"pos": "n", "trans": "长度；长"}]}, {"word": "deed", "phon": "diːd", "mean": [{"pos": "n", "trans": "行动；事迹"}]}, {"word": "knight", "phon": "naɪt", "mean": [{"pos": "n", "trans": "骑士；爵士"}]}, {"word": "sword", "phon": "sɔːd", "mean": [{"pos": "n", "trans": "剑"}]}, {"word": "joust", "phon": "dʒaʊst", "mean": [{"pos": "v", "trans": "（指中世纪骑士）骑着马用长予打斗"}]}, {"word": "tournament", "phon": "ˈtɔ:nəmənt", "mean": [{"pos": "n", "trans": "锦标赛；联赛"}]}, {"word": "settler", "phon": "'setlə", "mean": [{"pos": "n", "trans": "移民；殖民者"}]}, {"word": "athletic", "phon": "æθ'letɪk", "mean": [{"pos": "adj", "trans": "运动的"}]}, {"word": "translator", "phon": "træns'leɪtə; trɑːns-; -nz-", "mean": [{"pos": "n", "trans": "译员；翻译"}]}, {"word": "minority", "phon": "maɪ'nɒrɪtɪ; mɪ-", "mean": [{"pos": "n", "trans": "少数；少数民族"}]}, {"word": "cloth", "phon": "klɒθ", "mean": [{"pos": "n", "trans": "布"}]}, {"word": "jungle", "phon": "'dʒʌŋg(ə)l", "mean": [{"pos": "n", "trans": "丛林"}]}, {"word": "diver", "phon": "'daɪvə", "mean": [{"pos": "n", "trans": "潜水员"}]}, {"word": "creature", "phon": "'kriːtʃə", "mean": [{"pos": "n", "trans": "生物；动物"}]}, {"word": "sunlight", "phon": "'sʌnlaɪt", "mean": [{"pos": "n", "trans": "阳光"}]}, {"word": "advance", "phon": "əd'vɑːns", "mean": [{"pos": "v", "trans": "前进；提前"}]}, {"word": "advanced", "phon": "ədˈvɑ:nst", "mean": [{"pos": "adj", "trans": "高级的；先进的"}]}, {"word": "brand", "phon": "brænd", "mean": [{"pos": "n", "trans": "商标；牌子"}]}, {"word": "outing", "phon": "'aʊtɪŋ", "mean": [{"pos": "n", "trans": "外出；短途旅行；远足"}]}, {"word": "admission", "phon": "əd'mɪʃ(ə)n", "mean": [{"pos": "n", "trans": "承认；准许进(加)入；入场费"}]}, {"word": "shuttle", "phon": "'ʃʌt(ə)l", "mean": [{"pos": "n", "trans": "往返汽车；航天飞机"}]}, {"word": "freeway", "phon": "'friːweɪ", "mean": [{"pos": "n", "trans": "高速公路"}]}, {"word": "souvenir", "phon": ",suːvə'nɪə", "mean": [{"pos": "n", "trans": "纪念品"}]}, {"word": "sneaker", "phon": "'sniːkə", "mean": [{"pos": "n", "trans": "运动鞋"}]}, {"word": "brochure", "phon": "'brəʊʃə; brɒ'ʃʊə", "mean": [{"pos": "n", "trans": "（作宣传或介绍用的）小册子；指南"}]}]