[{"word": "pair", "phon": "peə", "mean": [{"pos": "n", "trans": "（相关的）两个人，一对"}]}, {"word": "correct", "phon": "kə'rekt", "mean": [{"pos": "v", "trans": "改正；纠正"}, {"pos": "adj", "trans": "正确的；对的"}]}, {"word": "spelling", "phon": "'spelɪŋ", "mean": [{"pos": "n", "trans": "拼写"}]}, {"word": "word", "phon": "wɜːd", "mean": [{"pos": "n", "trans": "词；单词；字"}]}, {"word": "practise", "phon": "'præktɪs", "mean": [{"pos": "v", "trans": "练习"}]}, {"word": "match", "phon": "mætʃ", "mean": [{"pos": "v", "trans": "找到与⋯⋯相配之物，使相配；使成对"}]}, {"word": "meaning", "phon": "'miːnɪŋ", "mean": [{"pos": "n", "trans": "意义；意思"}]}, {"word": "complete", "phon": "kəm'pliːt", "mean": [{"pos": "v", "trans": "把⋯⋯填完整；使完全"}]}, {"word": "sentence", "phon": "'sent(ə)ns", "mean": [{"pos": "n", "trans": "句子"}]}, {"word": "dictionary", "phon": "'dɪkʃ(ə)n(ə)rɪ", "mean": [{"pos": "n", "trans": "词典；字典"}]}, {"word": "grammar", "phon": "'græmə", "mean": [{"pos": "n", "trans": "语法"}]}, {"word": "letter", "phon": "'letə", "mean": [{"pos": "n", "trans": "字母"}]}, {"word": "mistake", "phon": "mɪ'steɪk", "mean": [{"pos": "n", "trans": "错误；过错"}]}, {"word": "understand", "phon": "ʌndə'stænd", "mean": [{"pos": "v", "trans": "(understood) 理解；明白"}]}, {"word": "advice", "phon": "əd'vaɪs", "mean": [{"pos": "n", "trans": "意见；建议"}]}, {"word": "should", "phon": "ʃəd; strong form ʃʊd", "mean": [{"pos": "v aux", "trans": "应该"}]}, {"word": "possible", "phon": "'pɒsɪb(ə)l", "mean": [{"pos": "adj", "trans": "可能的"}]}, {"word": "notebook", "phon": "'nəʊtbʊk", "mean": [{"pos": "n", "trans": "笔记本"}]}, {"word": "forget", "phon": "fə'get", "mean": [{"pos": "v", "trans": "(forgot) 忘；忘记"}]}, {"word": "pronounce", "phon": "prə'naʊns", "mean": [{"pos": "v", "trans": "发⋯⋯的音"}]}, {"word": "aloud", "phon": "ə'laʊd", "mean": [{"pos": "adv", "trans": "大声地；出声地"}]}, {"word": "radio", "phon": "'reɪdɪəʊ", "mean": [{"pos": "n", "trans": "电台；广播"}]}, {"word": "pronunciation", "phon": "prə,nʌnsɪ'eɪʃ(ə)n", "mean": [{"pos": "n", "trans": "发音"}]}, {"word": "key", "phon": "kiː", "mean": [{"pos": "adj", "trans": "关键性的，非常重要的"}]}, {"word": "main", "phon": "meɪn", "mean": [{"pos": "adj", "trans": "主要的；最大的"}]}, {"word": "excellent", "phon": "ˈeksələnt", "mean": [{"pos": "adj", "trans": "极好的；优秀的"}]}, {"word": "agree", "phon": "ə'griː", "mean": [{"pos": "v", "trans": "赞同"}]}, {"word": "vocabulary", "phon": "və(ʊ)'kæbjʊlərɪ", "mean": [{"pos": "n", "trans": "词汇；词汇量"}]}, {"word": "improve", "phon": "ɪm'pruːv", "mean": [{"pos": "v", "trans": "改进；改善"}]}, {"word": "basic", "phon": "'beɪsɪk", "mean": [{"pos": "adj", "trans": "主要的；基础的"}]}, {"word": "time", "phon": "taɪm", "mean": [{"pos": "n", "trans": "次；回"}]}, {"word": "advise", "phon": "əd'vaɪz", "mean": [{"pos": "v", "trans": "向⋯⋯提出意见；忠告；建议"}]}, {"word": "shy", "phon": "ʃaɪ", "mean": [{"pos": "adj", "trans": "羞怯的；腼腆的"}]}, {"word": "conversation", "phon": "kɒnvə'seɪʃ(ə)n", "mean": [{"pos": "n", "trans": "谈话；交谈"}]}, {"word": "quickly", "phon": "'kwɪklɪ", "mean": [{"pos": "adv", "trans": "快地；迅速地"}]}, {"word": "natural", "phon": "ˈnætʃrəl", "mean": [{"pos": "adj", "trans": "合理的；合乎常情的"}]}, {"word": "suggest", "phon": "sə'dʒest", "mean": [{"pos": "v", "trans": "建议；提议"}]}, {"word": "place", "phon": "pleɪs", "mean": [{"pos": "v", "trans": "放置"}]}, {"word": "hill", "phon": "hɪl", "mean": [{"pos": "n", "trans": "小山；小丘"}]}, {"word": "population", "phon": "pɒpjʊ'leɪʃ(ə)n", "mean": [{"pos": "n", "trans": "（某一地区的）人口，全体居民"}]}, {"word": "wide", "phon": "waɪd", "mean": [{"pos": "adj", "trans": "宽的；宽阔的"}]}, {"word": "million", "phon": "'mɪljən", "mean": [{"pos": "num", "trans": "百万"}]}, {"word": "pretty", "phon": "'prɪtɪ", "mean": [{"pos": "adv", "trans": "[主口]相当地；非常；很"}]}, {"word": "than", "phon": "ðæn; ð(ə)n", "mean": [{"pos": "prep", "trans": "比"}]}, {"word": "get", "phon": "get", "mean": [{"pos": "v", "trans": "成为；变成"}]}, {"word": "north", "phon": "nɔːθ", "mean": [{"pos": "n", "trans": "北；北方"}, {"pos": "adj", "trans": "在北方的；朝北的"}]}, {"word": "south", "phon": "saʊθ", "mean": [{"pos": "n", "trans": "南；南方"}, {"pos": "adj", "trans": "在南方的；朝南的"}]}, {"word": "west", "phon": "west", "mean": [{"pos": "n", "trans": "西；西方"}, {"pos": "adj", "trans": "在西方的；朝西的"}]}, {"word": "especially", "phon": "ɪˈspeʃəlɪ", "mean": [{"pos": "adv", "trans": "尤其"}]}, {"word": "university", "phon": "juːnɪ'vɜːsɪtɪ", "mean": [{"pos": "n", "trans": "大学"}]}, {"word": "island", "phon": "'aɪlənd", "mean": [{"pos": "n", "trans": "岛；岛屿"}]}, {"word": "area", "phon": "'eərɪə", "mean": [{"pos": "n", "trans": "地区；区域"}]}, {"word": "low", "phon": "ləʊ", "mean": [{"pos": "adj", "trans": "矮的；低的"}]}, {"word": "mountain", "phon": "ˈmaʊntən", "mean": [{"pos": "n", "trans": "山；山岳"}]}, {"word": "countryside", "phon": "'kʌntrɪsaɪd", "mean": [{"pos": "n", "trans": "农村地区；乡下"}]}, {"word": "umbrella", "phon": "ʌm'brelə", "mean": [{"pos": "n", "trans": "雨伞"}]}, {"word": "baseball", "phon": "'beɪsbɔːl", "mean": [{"pos": "n", "trans": "棒球"}]}, {"word": "volleyball", "phon": "'vɒlɪbɔːl", "mean": [{"pos": "n", "trans": "排球"}]}, {"word": "boring", "phon": "'bɔːrɪŋ", "mean": [{"pos": "adj", "trans": "烦人的；无聊的"}]}, {"word": "exciting", "phon": "ɪk'saɪtɪŋ; ek-", "mean": [{"pos": "adj", "trans": "令人激动的；使人兴奋的"}]}, {"word": "relaxing", "phon": "rɪ'læksɪŋ", "mean": [{"pos": "adj", "trans": "令人愉悦的；使人放松的"}]}, {"word": "score", "phon": "skɔː", "mean": [{"pos": "v", "trans": "（体育比赛中）得（分）"}]}, {"word": "already", "phon": "ɔːl'redɪ", "mean": [{"pos": "adv", "trans": "已经；早已"}]}, {"word": "matter", "phon": "'mætə", "mean": [{"pos": "n", "trans": "问题；麻烦"}]}, {"word": "hurt", "phon": "hɜːt", "mean": [{"pos": "v", "trans": "(hurt) （使）疼痛；（使）受伤"}]}, {"word": "enjoyable", "phon": "ɪn'dʒɒɪəb(ə)l; en-", "mean": [{"pos": "adj", "trans": "令人愉快的；有乐趣的"}]}, {"word": "stadium", "phon": "'steɪdɪəm", "mean": [{"pos": "n", "trans": "体育场"}]}, {"word": "miss", "phon": "mɪs", "mean": [{"pos": "v", "trans": "未击中；未达到"}]}, {"word": "mind", "phon": "maɪnd", "mean": [{"pos": "v", "trans": "介意；讨厌；反对"}]}, {"word": "plenty", "phon": "'plentɪ", "mean": [{"pos": "pron", "trans": "大量；众多"}]}, {"word": "beat", "phon": "biːt", "mean": [{"pos": "v", "trans": "(beat) 打败；战胜"}]}, {"word": "careless", "phon": "'keələs", "mean": [{"pos": "adj", "trans": "粗心的；疏忽的"}]}, {"word": "coach", "phon": "kəʊtʃ", "mean": [{"pos": "n", "trans": "教练"}]}, {"word": "against", "phon": "ə'genst; ə'geɪnst", "mean": [{"pos": "prep", "trans": "（在比赛或战斗中）对（某人或某事物）"}]}, {"word": "train", "phon": "treɪn", "mean": [{"pos": "v", "trans": "（体育）训练，操练"}]}, {"word": "practice", "phon": "'præktɪs", "mean": [{"pos": "n", "trans": "练习"}]}, {"word": "warm", "phon": "wɔːm", "mean": [{"pos": "v", "trans": "使暖和；使温暖"}]}, {"word": "usual", "phon": "'juːʒʊəl", "mean": [{"pos": "adj", "trans": "通常的；平常的"}]}, {"word": "better", "phon": "'betə", "mean": [{"pos": "adv", "trans": "更好地"}, {"pos": "adj", "trans": "更好的"}]}, {"word": "pleased", "phon": "pliːzd", "mean": [{"pos": "adj", "trans": "开心的；满足的"}]}, {"word": "pass", "phon": "pɑːs", "mean": [{"pos": "v", "trans": "传递；传送"}]}, {"word": "pity", "phon": "'pɪtɪ", "mean": [{"pos": "n", "trans": "可惜；遗憾"}]}, {"word": "chance", "phon": "tʃɑːns", "mean": [{"pos": "n", "trans": "可能性；机会"}]}, {"word": "loudly", "phon": "'laʊdlɪ", "mean": [{"pos": "adv", "trans": "响亮地；大声地"}]}, {"word": "confident", "phon": "'kɒnfɪd(ə)nt", "mean": [{"pos": "adj", "trans": "自信的"}]}, {"word": "road", "phon": "rəʊd", "mean": [{"pos": "n", "trans": "路；（尤指）公路"}]}, {"word": "accident", "phon": "'æksɪdənt", "mean": [{"pos": "n", "trans": "交通事故；意外事件"}]}, {"word": "except", "phon": "ɪkˈsept", "mean": [{"pos": "prep", "trans": "除⋯⋯之外"}]}, {"word": "choice", "phon": "tʃɒɪs", "mean": [{"pos": "n", "trans": "选择"}]}, {"word": "classmate", "phon": "'klɑːsmeɪt", "mean": [{"pos": "n", "trans": "同班同学"}]}, {"word": "far", "phon": "fɑː", "mean": [{"pos": "adv", "trans": "远；遥远"}, {"pos": "adj", "trans": "远的；遥远的"}]}, {"word": "close", "phon": "kləʊs", "mean": [{"pos": "adj", "trans": "（距离上）近的，接近的"}, {"pos": "adv", "trans": "（距离上）接近地"}]}, {"word": "crowded", "phon": "'kraʊdɪd", "mean": [{"pos": "adj", "trans": "拥挤的；人数过多的"}]}, {"word": "journey", "phon": "'dʒɜːnɪ", "mean": [{"pos": "n", "trans": "旅行；旅程"}]}, {"word": "book", "phon": "bʊk", "mean": [{"pos": "v", "trans": "预订"}]}, {"word": "park", "phon": "pɑːk", "mean": [{"pos": "v", "trans": "停放（车）；泊（车）"}]}, {"word": "outside", "phon": "aʊt'saɪd; 'aʊtsaɪd", "mean": [{"pos": "prep", "trans": "在⋯⋯之外"}, {"pos": "adv", "trans": "在外面；朝户外"}, {"pos": "n", "trans": "外面；外部"}, {"pos": "adj", "trans": "外部的；外表的"}]}, {"word": "however", "phon": "haʊ'evə", "mean": [{"pos": "adv", "trans": "然而；但是"}]}, {"word": "cost", "phon": "kɒst", "mean": [{"pos": "v", "trans": "(cost) 价钱为；花费"}, {"pos": "n", "trans": "价钱；成本；代价"}]}, {"word": "actress", "phon": "'æktrɪs", "mean": [{"pos": "n", "trans": "女演员"}]}, {"word": "teahouse", "phon": "'tiːhaʊs", "mean": [{"pos": "n", "trans": "（尤指亚洲的）茶馆"}]}, {"word": "offer", "phon": "'ɒfə", "mean": [{"pos": "v", "trans": "提议；提出"}]}, {"word": "end", "phon": "end", "mean": [{"pos": "n", "trans": "（时间的）最后一段，末尾"}, {"pos": "v", "trans": "结束"}]}, {"word": "act", "phon": "ækt", "mean": [{"pos": "n", "trans": "（戏剧、歌剧或芭蕾舞的）一幕"}]}, {"word": "show", "phon": "ʃəʊ", "mean": [{"pos": "v", "trans": "展示；显示"}, {"pos": "n", "trans": "演出；表演"}]}, {"word": "common", "phon": "'kɒmən", "mean": [{"pos": "adj", "trans": "普通的；一般的"}]}, {"word": "twentieth", "phon": "ˈtwentɪəθ", "mean": [{"pos": "num", "trans": "第二十"}]}, {"word": "describe", "phon": "dɪ'skraɪb", "mean": [{"pos": "v", "trans": "描写；描述"}]}, {"word": "society", "phon": "sə'saɪətɪ", "mean": [{"pos": "n", "trans": "社会"}]}, {"word": "college", "phon": "'kɒlɪdʒ", "mean": [{"pos": "n", "trans": "大学；学院"}]}, {"word": "novel", "phon": "'nɒv(ə)l", "mean": [{"pos": "n", "trans": "（长篇）小说"}]}, {"word": "name", "phon": "neɪm", "mean": [{"pos": "v", "trans": "给⋯⋯取名；给⋯⋯命名"}]}, {"word": "if", "phon": "ɪf", "mean": [{"pos": "conj", "trans": "如果；若"}]}, {"word": "magic", "phon": "'mædʒɪk", "mean": [{"pos": "adj", "trans": "魔术的；戏法的"}]}, {"word": "snake", "phon": "sneɪk", "mean": [{"pos": "n", "trans": "蛇"}]}, {"word": "neck", "phon": "nek", "mean": [{"pos": "n", "trans": "颈；脖子"}]}, {"word": "thin", "phon": "θɪn", "mean": [{"pos": "adj", "trans": "薄的；细长的"}]}, {"word": "danger", "phon": "ˈdeɪndʒə(r)", "mean": [{"pos": "n", "trans": "危险；危害"}]}, {"word": "interested", "phon": "'ɪntrəstɪd", "mean": [{"pos": "adj", "trans": "关心的；感兴趣的"}]}, {"word": "allow", "phon": "ə'laʊ", "mean": [{"pos": "v", "trans": "允许；准许"}]}, {"word": "protect", "phon": "prə'tekt", "mean": [{"pos": "v", "trans": "保护；保卫"}]}, {"word": "wild", "phon": "waɪld", "mean": [{"pos": "adj", "trans": "野生的"}, {"pos": "n", "trans": "野生环境"}]}, {"word": "grow", "phon": "grəʊ", "mean": [{"pos": "v", "trans": "(grew) （逐渐）变得；生长"}]}, {"word": "enough", "phon": "ɪ'nʌf", "mean": [{"pos": "adj", "trans": "足够的；充分的"}]}, {"word": "peace", "phon": "piːs", "mean": [{"pos": "n", "trans": "和平；太平"}]}, {"word": "notice", "phon": "'nəʊtɪs", "mean": [{"pos": "n", "trans": "布告；告示"}]}, {"word": "raise", "phon": "reɪz", "mean": [{"pos": "v", "trans": "筹集（钱款）；抚养；养育"}]}, {"word": "research", "phon": "rɪ'sɜːtʃ; 'riːsɜːtʃ", "mean": [{"pos": "n", "trans": "研究；探讨"}]}, {"word": "baby", "phon": "'beɪbɪ", "mean": [{"pos": "n", "trans": "婴儿；婴孩"}]}, {"word": "situation", "phon": "sɪtjʊ'eɪʃ(ə)n", "mean": [{"pos": "n", "trans": "形势；情况"}]}, {"word": "scientist", "phon": "'saɪəntɪst", "mean": [{"pos": "n", "trans": "科学家"}]}, {"word": "produce", "phon": "prəˈdju:s;(for n.)ˈprɒdju:s", "mean": [{"pos": "v", "trans": "生育；繁殖"}]}, {"word": "southwest", "phon": ",saʊθ'west", "mean": [{"pos": "n", "trans": "西南"}, {"pos": "adj", "trans": "西南的；朝西南的"}]}, {"word": "government", "phon": "ˈgʌvənmənt", "mean": [{"pos": "n", "trans": "政府"}]}, {"word": "set", "phon": "set", "mean": [{"pos": "v", "trans": "设置；设定"}]}, {"word": "nature", "phon": "'neɪtʃə", "mean": [{"pos": "n", "trans": "大自然；自然界"}]}, {"word": "develop", "phon": "dɪ'veləp", "mean": [{"pos": "v", "trans": "研制；制定"}]}, {"word": "feed", "phon": "fiːd", "mean": [{"pos": "v", "trans": "(fed) 喂养；饲养"}]}, {"word": "symbol", "phon": "'sɪmb(ə)l", "mean": [{"pos": "n", "trans": "象征；标志"}]}, {"word": "fall", "phon": "fɔːl", "mean": [{"pos": "v", "trans": "(fell) 下落；跌落"}]}, {"word": "follow", "phon": "'fɒləʊ", "mean": [{"pos": "v", "trans": "跟随；紧跟"}]}, {"word": "hole", "phon": "həʊl", "mean": [{"pos": "n", "trans": "洞，孔；穴"}]}, {"word": "rabbit", "phon": "'ræbɪt", "mean": [{"pos": "n", "trans": "兔；家兔"}]}, {"word": "ground", "phon": "graʊnd", "mean": [{"pos": "n", "trans": "地面"}]}, {"word": "twice", "phon": "twaɪs", "mean": [{"pos": "adv", "trans": "两次；两倍"}]}, {"word": "suddenly", "phon": "ˈsʌdnlɪ", "mean": [{"pos": "adv", "trans": "突然地；出乎意料地"}]}, {"word": "pink", "phon": "pɪŋk", "mean": [{"pos": "adj", "trans": "粉红色的"}, {"pos": "n", "trans": "粉红色"}]}, {"word": "pocket", "phon": "'pɒkɪt", "mean": [{"pos": "n", "trans": "衣袋；口袋"}]}, {"word": "field", "phon": "fiːld", "mean": [{"pos": "n", "trans": "牧场；田地"}]}, {"word": "deep", "phon": "diːp", "mean": [{"pos": "adj", "trans": "（从顶部向下）深的"}]}, {"word": "while", "phon": "waɪl", "mean": [{"pos": "conj", "trans": "当⋯⋯的时候"}]}, {"word": "land", "phon": "lænd", "mean": [{"pos": "v", "trans": "降落（或跳落、跌落）到地面（或水面上）"}]}, {"word": "dry", "phon": "draɪ", "mean": [{"pos": "adj", "trans": "干的；干燥的"}]}, {"word": "pale", "phon": "peɪl", "mean": [{"pos": "adj", "trans": "（肤色）苍白的"}]}, {"word": "appear", "phon": "ə'pɪə", "mean": [{"pos": "v", "trans": "出现；显露"}]}, {"word": "round", "phon": "raʊnd", "mean": [{"pos": "prep", "trans": "转到（某物的）另一边"}]}, {"word": "corner", "phon": "'kɔːnə", "mean": [{"pos": "n", "trans": "拐角；街角"}]}, {"word": "hit", "phon": "hɪt", "mean": [{"pos": "v", "trans": "(hit) （使）碰撞"}]}, {"word": "glad", "phon": "glæd", "mean": [{"pos": "adj", "trans": "高兴的；欢喜的"}]}, {"word": "risk", "phon": "rɪsk", "mean": [{"pos": "n", "trans": "危险；风险"}]}, {"word": "attention", "phon": "ə'tenʃ(ə)n", "mean": [{"pos": "n", "trans": "注意力"}]}, {"word": "side", "phon": "saɪd", "mean": [{"pos": "n", "trans": "（物体或形状的）侧面"}]}, {"word": "bite", "phon": "baɪt", "mean": [{"pos": "v", "trans": "(bit) 咬；叮"}]}, {"word": "climb", "phon": "klaɪm", "mean": [{"pos": "v", "trans": "爬；攀爬"}]}, {"word": "hide", "phon": "haɪd", "mean": [{"pos": "v", "trans": "(hid) 躲；躲藏"}]}, {"word": "throw", "phon": "θrəʊ", "mean": [{"pos": "v", "trans": "(threw) 扔；掷"}]}, {"word": "fridge", "phon": "frɪdʒ", "mean": [{"pos": "n", "trans": "冰箱"}]}, {"word": "pain", "phon": "peɪn", "mean": [{"pos": "n", "trans": "痛；疼痛"}]}, {"word": "worse", "phon": "wəːs", "mean": [{"pos": "adj", "trans": "更糟的；更坏的"}, {"pos": "adv", "trans": "更糟；更严重"}]}, {"word": "medicine", "phon": "ˈmedsn", "mean": [{"pos": "n", "trans": "药；药物"}]}, {"word": "noise", "phon": "nɔɪz", "mean": [{"pos": "n", "trans": "噪声；杂音"}]}, {"word": "prepare", "phon": "prɪ'peə", "mean": [{"pos": "v", "trans": "准备；预备"}]}, {"word": "notes", "phon": "nəʊts", "mean": [{"pos": "n", "trans": "笔记；随笔 (pl.)"}]}, {"word": "report", "phon": "rɪ'pɔːt", "mean": [{"pos": "n", "trans": "报告；汇报"}]}, {"word": "Grow", "phon": "grəʊ", "mean": [{"pos": "v", "trans": "(grew) 增长；增大"}]}, {"word": "huge", "phon": "hjuːdʒ", "mean": [{"pos": "adj", "trans": "巨大的；庞大的"}]}, {"word": "cause", "phon": "kɔːz", "mean": [{"pos": "v", "trans": "造成；引起"}]}, {"word": "problem", "phon": "'prɒbləm", "mean": [{"pos": "n", "trans": "麻烦；问题"}]}, {"word": "increase", "phon": "ɪn'kriːs", "mean": [{"pos": "v", "trans": "增大；增长"}]}, {"word": "birth", "phon": "bɜːθ", "mean": [{"pos": "n", "trans": "出生"}]}, {"word": "billion", "phon": "'bɪljən", "mean": [{"pos": "num", "trans": "十亿"}]}, {"word": "fifth", "phon": "fɪfθ", "mean": [{"pos": "num", "trans": "第五；五分之一"}]}, {"word": "flat", "phon": "flæt", "mean": [{"pos": "n", "trans": "套房；公寓"}]}, {"word": "rubbish", "phon": "'rʌbɪʃ", "mean": [{"pos": "n", "trans": "垃圾；废弃物"}]}, {"word": "quiet", "phon": "'kwaɪət", "mean": [{"pos": "adj", "trans": "寂静的；安静的"}]}, {"word": "local", "phon": "'ləʊk(ə)l", "mean": [{"pos": "adj", "trans": "当地的；本地的"}]}, {"word": "pupil", "phon": "'pjuːpɪl; -p(ə)l", "mean": [{"pos": "n", "trans": "学生；（尤指）小学生"}]}, {"word": "pollution", "phon": "pə'luːʃ(ə)n", "mean": [{"pos": "n", "trans": "污染"}]}, {"word": "public", "phon": "'pʌblɪk", "mean": [{"pos": "adj", "trans": "公共的；公众的"}]}, {"word": "service", "phon": "'sɜːvɪs", "mean": [{"pos": "n", "trans": "公共服务；服务"}]}, {"word": "solve", "phon": "sɒlv", "mean": [{"pos": "v", "trans": "解决问题"}]}, {"word": "cloud", "phon": "klaʊd", "mean": [{"pos": "n", "trans": "云；云雾"}]}, {"word": "shower", "phon": "'ʃaʊə", "mean": [{"pos": "n", "trans": "阵雨"}]}, {"word": "snow", "phon": "snəʊ", "mean": [{"pos": "n", "trans": "雪"}, {"pos": "v", "trans": "下雪"}]}, {"word": "storm", "phon": "stɔːm", "mean": [{"pos": "n", "trans": "暴风雨"}]}, {"word": "cloudy", "phon": "'klaʊdɪ", "mean": [{"pos": "adj", "trans": "多云的"}]}, {"word": "rainy", "phon": "'reɪnɪ", "mean": [{"pos": "adj", "trans": "多雨的；下雨的"}]}, {"word": "snowy", "phon": "'snəʊɪ", "mean": [{"pos": "adj", "trans": "多雪的；下雪的"}]}, {"word": "sunny", "phon": "'sʌnɪ", "mean": [{"pos": "adj", "trans": "晴朗的"}]}, {"word": "windy", "phon": "'wɪndɪ", "mean": [{"pos": "adj", "trans": "多风的；刮大风的"}]}, {"word": "skate", "phon": "skeɪt", "mean": [{"pos": "v", "trans": "滑冰"}]}, {"word": "thick", "phon": "θɪk", "mean": [{"pos": "adj", "trans": "厚的"}]}, {"word": "ice", "phon": "aɪs", "mean": [{"pos": "n", "trans": "冰"}]}, {"word": "joke", "phon": "dʒəʊk", "mean": [{"pos": "v", "trans": "说笑话；开玩笑"}, {"pos": "n", "trans": "笑话；玩笑"}]}, {"word": "might", "phon": "maɪt", "mean": [{"pos": "v aux", "trans": "可能；也许"}]}, {"word": "temperature", "phon": "temprətʃə(r)", "mean": [{"pos": "n", "trans": "温度"}]}, {"word": "minus", "phon": "'maɪnəs", "mean": [{"pos": "adj", "trans": "负的；零下的"}]}, {"word": "degree", "phon": "dɪ'griː", "mean": [{"pos": "n", "trans": "度；度数"}]}, {"word": "although", "phon": "ɔːl'ðəʊ; ɒl-", "mean": [{"pos": "conj", "trans": "然而；尽管"}]}, {"word": "wet", "phon": "wet", "mean": [{"pos": "adj", "trans": "下雨的；湿的"}]}, {"word": "neither", "phon": "ˈnaɪðə; ˈniːðə", "mean": [{"pos": "adv", "trans": "（某人或某事物）也不"}]}, {"word": "terrible", "phon": "ˈterəbl", "mean": [{"pos": "adj", "trans": "使人烦恼的；可怕的"}]}, {"word": "wish", "phon": "wɪʃ", "mean": [{"pos": "v", "trans": "但愿；希望"}]}, {"word": "probably", "phon": "'prɒbəblɪ", "mean": [{"pos": "adv", "trans": "或许；可能"}]}, {"word": "mile", "phon": "maɪl", "mean": [{"pos": "n", "trans": "英里"}]}, {"word": "Round", "phon": "raʊnd", "mean": [{"pos": "adv", "trans": "围绕地"}]}, {"word": "northwest", "phon": ",nɔ:θ'west", "mean": [{"pos": "n", "trans": "西北"}, {"pos": "adj", "trans": "西北的；朝西北的"}]}, {"word": "southeast", "phon": ",saʊθ'iːst", "mean": [{"pos": "n", "trans": "东南"}, {"pos": "adj", "trans": "东南的；朝东南的"}]}, {"word": "cap", "phon": "kæp", "mean": [{"pos": "n", "trans": "（有檐的）帽子"}]}, {"word": "chess", "phon": "tʃes", "mean": [{"pos": "n", "trans": "国际象棋"}]}, {"word": "set", "phon": "set", "mean": [{"pos": "n", "trans": "（同类事物的）（一）套，（一）副，（一）组"}]}, {"word": "chopstick", "phon": "'tʃɒpstɪk", "mean": [{"pos": "n", "trans": "筷子"}]}, {"word": "toy", "phon": "tɒɪ", "mean": [{"pos": "n", "trans": "玩具"}]}, {"word": "video", "phon": "'vɪdɪəʊ", "mean": [{"pos": "adj", "trans": "（电子）视频的"}]}, {"word": "gift", "phon": "gɪft", "mean": [{"pos": "n", "trans": "礼物"}]}, {"word": "surprise", "phon": "sə'praɪz", "mean": [{"pos": "n", "trans": "惊奇；意外之事"}, {"pos": "v", "trans": "使（某人）吃惊"}]}, {"word": "immediately", "phon": "ɪ'miːdɪətlɪ", "mean": [{"pos": "adv", "trans": "立刻；当即"}]}, {"word": "difference", "phon": "'dɪf(ə)r(ə)ns", "mean": [{"pos": "n", "trans": "差别；差异"}]}, {"word": "accept", "phon": "əkˈsept", "mean": [{"pos": "v", "trans": "收受；接受"}]}, {"word": "tradition", "phon": "trə'dɪʃ(ə)n", "mean": [{"pos": "n", "trans": "传统习俗"}]}, {"word": "example", "phon": "ɪg'zɑːmp(ə)l; eg-", "mean": [{"pos": "n", "trans": "例子；实例"}]}, {"word": "must", "phon": "mʌst", "mean": [{"pos": "v aux", "trans": "必须；应该"}]}, {"word": "month", "phon": "mʌnθ", "mean": [{"pos": "n", "trans": "月；月份"}]}, {"word": "serious", "phon": "'sɪərɪəs", "mean": [{"pos": "adj", "trans": "认真严肃的；不开玩笑的"}]}, {"word": "taste", "phon": "teɪst", "mean": [{"pos": "v", "trans": "有⋯⋯的味道"}, {"pos": "n", "trans": "味道；滋味"}]}, {"word": "experience", "phon": "ɪkˈspɪərɪəns", "mean": [{"pos": "n", "trans": "经历；经验"}]}, {"word": "stay", "phon": "steɪ", "mean": [{"pos": "n", "trans": "逗留；停留"}]}, {"word": "someone", "phon": "'sʌmwʌn", "mean": [{"pos": "pron", "trans": "某人；有人"}]}, {"word": "sandwich", "phon": "'sæn(d)wɪdʒ; -wɪtʃ", "mean": [{"pos": "n", "trans": "三明治；夹心面包片"}]}, {"word": "chip", "phon": "tʃɪp", "mean": [{"pos": "n", "trans": "炸土豆条；炸薯条"}]}, {"word": "onto", "phon": "'ɒntuː", "mean": [{"pos": "prep", "trans": "到⋯⋯之上；向⋯⋯之上"}]}, {"word": "gentleman", "phon": "'dʒent(ə)lmən", "mean": [{"pos": "n", "trans": "先生；男士"}]}, {"word": "shoulder", "phon": "'ʃəʊldə", "mean": [{"pos": "n", "trans": "肩；肩膀"}]}, {"word": "broken", "phon": "'brəʊk(ə)n", "mean": [{"pos": "adj", "trans": "破碎的"}]}, {"word": "glass", "phon": "glɑːs", "mean": [{"pos": "n", "trans": "玻璃"}]}, {"word": "stairs", "phon": "stɛəz", "mean": [{"pos": "n", "trans": "楼梯 (pl.)"}]}, {"word": "aid", "phon": "eɪd", "mean": [{"pos": "n", "trans": "救助；帮助"}]}, {"word": "medical", "phon": "'medɪk(ə)l", "mean": [{"pos": "adj", "trans": "医学的；医疗的"}]}, {"word": "imagine", "phon": "ɪ'mædʒɪn", "mean": [{"pos": "v", "trans": "想像，设想"}]}, {"word": "bottom", "phon": "'bɒtəm", "mean": [{"pos": "n", "trans": "底部；下端"}]}, {"word": "wrong", "phon": "rɒŋ", "mean": [{"pos": "adj", "trans": "有毛病的；错误的"}, {"pos": "adv", "trans": "不正确地；错误地"}]}, {"word": "trouble", "phon": "'trʌb(ə)l", "mean": [{"pos": "n", "trans": "问题；烦恼；困难"}]}, {"word": "lift", "phon": "lɪft", "mean": [{"pos": "v", "trans": "举起；抬起；提起"}, {"pos": "n", "trans": "电梯"}]}, {"word": "harmful", "phon": "'hɑːmfʊl; -f(ə)l", "mean": [{"pos": "adj", "trans": "有害的"}]}, {"word": "drop", "phon": "drɒp", "mean": [{"pos": "v", "trans": "使落下；投下"}]}, {"word": "training", "phon": "'treɪnɪŋ", "mean": [{"pos": "n", "trans": "训练；培训"}]}, {"word": "cover", "phon": "'kʌvə", "mean": [{"pos": "v", "trans": "盖；盖上"}]}, {"word": "earthquake", "phon": "'ɜːθkweɪk", "mean": [{"pos": "n", "trans": "地震"}]}, {"word": "warn", "phon": "wɔːn", "mean": [{"pos": "v", "trans": "警告；告诫"}]}, {"word": "inside", "phon": "ɪn'saɪd", "mean": [{"pos": "n", "trans": "内部；里面"}, {"pos": "adv", "trans": "在里面；向室内"}, {"pos": "prep", "trans": "在⋯⋯里面"}, {"pos": "prep", "trans": "在⋯⋯里面"}, {"pos": "adj", "trans": "里面的；内部的"}]}, {"word": "under", "phon": "'ʌndə", "mean": [{"pos": "prep", "trans": "在⋯⋯正下方；在⋯⋯下面"}]}, {"word": "window", "phon": "'wɪndəʊ", "mean": [{"pos": "n", "trans": "窗；窗户"}]}, {"word": "keep", "phon": "kiːp", "mean": [{"pos": "v", "trans": "(kept) 保持；留在"}]}, {"word": "clear", "phon": "klɪə", "mean": [{"pos": "adj", "trans": "不和⋯⋯接触的；不挨⋯⋯太近的"}, {"pos": "v", "trans": "清除；清理；移走"}]}, {"word": "calm", "phon": "kɑːm", "mean": [{"pos": "adj", "trans": "镇静的；沉着的"}]}, {"word": "brave", "phon": "breɪv", "mean": [{"pos": "adj", "trans": "勇敢的；无畏的"}]}, {"word": "helpful", "phon": "'helpfʊl; -f(ə)l", "mean": [{"pos": "adj", "trans": "有用的；提供帮助的"}]}, {"word": "power", "phon": "'paʊə", "mean": [{"pos": "n", "trans": "电；电力"}]}]
